{
    "width": 0.6,
    "height": 1.2,
    "left_flipper_x_min": 0.1,
    "left_flipper_x_max": 0.33999999999999997,
    "left_flipper_y_min": 0.8,
    "left_flipper_y_max": 0.9,
    "right_flipper_x_min": 0.6599999999999999,
    "right_flipper_x_max": 0.8999999999999999,
    "right_flipper_y_min": 0.8,
    "right_flipper_y_max": 0.9,
    "zones": [
        {
            "id": "default_left",
            "type": "left",
            "is_screen_space": true,
            "points": [
                {
                    "x": 0.15927175793978168,
                    "y": 0.8141918392677082
                },
                {
                    "x": 0.4592717579397817,
                    "y": 0.8141918392677082
                },
                {
                    "x": 0.4592717579397817,
                    "y": 1.0141918392677083
                },
                {
                    "x": 0.15927175793978168,
                    "y": 1.0141918392677083
                }
            ]
        },
        {
            "id": "default_right",
            "type": "right",
            "is_screen_space": true,
            "points": [
                {
                    "x": 0.5271889930539734,
                    "y": 0.8040072308688634
                },
                {
                    "x": 0.8271889930539733,
                    "y": 0.8040072308688634
                },
                {
                    "x": 0.8271889930539733,
                    "y": 1.0040072308688632
                },
                {
                    "x": 0.5271889930539734,
                    "y": 1.0040072308688632
                }
            ]
        }
    ],
    "bumpers": [
        {
            "x": 0.5,
            "y": 0.2,
            "radius_ratio": 0.03,
            "value": 200
        }
    ],
    "drop_targets": [
        {
            "x": 0.5,
            "y": 0.1,
            "width": 0.02,
            "height": 0.01,
            "value": 1000
        }
    ],
    "captures": [],
    "ramps": [],
    "teleports": [],
    "upper_deck": null,
    "upper_flippers": [],
    "physics": {
        "gravity": 1569.7629882328345,
        "friction": 0.43,
        "restitution": 0.78,
        "flipper_speed": 15.0,
        "flipper_resting_angle": -30.0,
        "flipper_stroke_angle": 50.0,
        "flipper_length": 0.24,
        "plunger_release_speed": 2500.0,
        "launch_angle": 0.0,
        "tilt_threshold": 1.0,
        "nudge_cost": 10.0,
        "tilt_decay": 0.117
    }
}